[
  {
    "id": "sitelink",
    "type": "inputstring",
    "name": "Site Link",
    "value": "https://rarbg.to/"
  },
  {
    "id": "cookieheader",
    "type": "hiddendata",
    "name": "CookieHeader",
    "value": "__cfduid=de39f2c295eeb4d93ab45d20193590d161603844962"
  },
  {
    "id": "lasterror",
    "type": "hiddendata",
    "name": "LastError",
    "value": null
  },
  {
    "id": "sortrequestedfromsite",
    "type": "inputselect",
    "name": "Sort requested from site",
    "value": "seeders",
    "options": {
      "last": "created",
      "seeders": "seeders",
      "leechers": "leechers"
    }
  }
]